bert/__init__.py
bert/attention.py
bert/bert.py
bert/embeddings.py
bert/layer.py
bert/loader.py
bert/model.py
bert/transformer.py
tests/compare/__init__.py
tests/compare/test_activations.py
tests/ext/__init__.py
tests/ext/modeling.py
tests/ext/tokenization.py
tests/nonci/__init__.py
tests/nonci/test_bert.py
tests/nonci/test_compare_pretrained.py
bert_for_tf2-0.1.1.dist-info/LICENSE
bert_for_tf2-0.1.1.dist-info/METADATA
bert_for_tf2-0.1.1.dist-info/WHEEL
bert_for_tf2-0.1.1.dist-info/top_level.txt
bert_for_tf2-0.1.1.dist-info/zip-safe
bert_for_tf2-0.1.1.dist-info/RECORD
