Metadata-Version: 2.1
Name: bert-for-tf2
Version: 0.1.1
Summary: A TensorFlow 2.0 Keras implementation of BERT.
Home-page: https://github.com/kpe/bert-for-tf2/
Author: kpe
Author-email: kpe.git@gmailbox.org
License: MIT
Keywords: tensorflow keras bert
Platform: UNKNOWN
Classifier: Development Status :: 5 - Production/Stable
Classifier: License :: OSI Approved :: MIT License
Classifier: Programming Language :: Python
Classifier: Programming Language :: Python :: 3
Classifier: Programming Language :: Python :: 3.6
Classifier: Programming Language :: Python :: 3.7
Classifier: Programming Language :: Python :: Implementation :: CPython
Classifier: Programming Language :: Python :: Implementation :: PyPy
Requires-Python: >=3.6
Requires-Dist: tensorflow (>=1.99)
Requires-Dist: py-params (>=0.6.1)
Requires-Dist: params-flow (>=0.2.1)
